rocket_releaser/__init__.py
rocket_releaser/__main__.py
rocket_releaser/changelog.py
rocket_releaser/graphql.py
rocket_releaser/prs.py
rocket_releaser/release_notes.py
rocket_releaser/shas.py
rocket_releaser/slack.py
rocket_releaser/ticket_labeler.py
tests/__init__.py
tests/test_changelog.py
tests/test_graphql.py
tests/test_prs.py
tests/test_release_notes.py
tests/test_shas.py
tests/test_ticket_labeler.py
rocket_releaser-0.1.0.dist-info/LICENSE
rocket_releaser-0.1.0.dist-info/METADATA
rocket_releaser-0.1.0.dist-info/WHEEL
rocket_releaser-0.1.0.dist-info/top_level.txt
rocket_releaser-0.1.0.dist-info/RECORD
