Metadata-Version: 2.1
Name: rocket-releaser
Version: 0.1.0
Summary: Script for release notes and labeling upon deploys
Home-page: https://github.com/15five/rocket_releaser
Author: 15Five
Author-email: caleb@15five.com
License: MIT
Keywords: release-notes release-automation
Platform: UNKNOWN
Classifier: Development Status :: 2 - Pre-Alpha
Classifier: Intended Audience :: Developers
Classifier: Intended Audience :: System Administrators
Classifier: License :: OSI Approved :: MIT License
Classifier: Operating System :: OS Independent
Classifier: Natural Language :: English
Classifier: Topic :: Software Development :: Libraries :: Python Modules
Classifier: Topic :: Internet
Classifier: Programming Language :: Python :: 3
Classifier: Programming Language :: Python :: 3.6
Classifier: Programming Language :: Python :: 3.7
Classifier: Programming Language :: Python :: 3.8
Requires-Python: >=3.6
Requires-Dist: jira (==2.0.0)
Requires-Dist: github3.py (==1.2.0)
Requires-Dist: gitdb2 (==3.0.1)
Requires-Dist: slacker (==0.9.65)
Requires-Dist: requests (==2.22.0)
